astrosa/__init__.py
astrosa/version.py
astrosa/assess/__init__.py
astrosa/assess/const.py
astrosa/assess/core.py
astrosa/assess/metrics.py
astrosa/assess/slew.py
astrosa/assess/telescope.py
astrosa/assess/transitioner.py
astrosa/assess/weather.py
astrosa/data/astrosa.sqlite
astrosa/healpix/__init__.py
astrosa/healpix/core.py
astrosa/plot/__init__.py
astrosa/plot/sky.py
astrosa/tests/__init__.py
astrosa/tests/test_core.py
astrosa/tests/test_metrics.py
astrosa/tests/test_slew.py
astrosa/tests/test_telescope.py
astrosa/tests/test_transitioner.py
astrosa/tests/test_weather.py
astrosa/tests/utils.py
astrosa-0.2.dist-info/LICENSE.txt
astrosa-0.2.dist-info/METADATA
astrosa-0.2.dist-info/WHEEL
astrosa-0.2.dist-info/top_level.txt
astrosa-0.2.dist-info/RECORD
