Metadata-Version: 2.1
Name: astrosa
Version: 0.2
Summary: Astronomical Observation Schedule Assessment Framework
Home-page: https://github.com/h-xie/astrosa
Author: H Xie
License: MIT
Requires-Python: >=3.10
License-File: LICENSE.txt
Requires-Dist: numpy >=1.17
Requires-Dist: astropy >=4
Requires-Dist: astroplan
Requires-Dist: rich
Requires-Dist: pandas
Requires-Dist: photutils
Requires-Dist: astropy-healpix
Requires-Dist: pytz
Requires-Dist: six
